geohub/__init__.py
geohub/common.py
geohub/foliumap.py
geohub/geohub.py
geohub-0.0.6.dist-info/LICENSE
geohub-0.0.6.dist-info/METADATA
geohub-0.0.6.dist-info/WHEEL
geohub-0.0.6.dist-info/entry_points.txt
geohub-0.0.6.dist-info/top_level.txt
geohub-0.0.6.dist-info/RECORD
