Metadata-Version: 2.1
Name: geohub
Version: 0.0.6
Summary: A python package created with some data and geospatial analysis skills
Author-email: Mahnaz Meem <mahnazsarkermeem@gmail.com>
License: BSD License
Project-URL: Homepage, https://github.com/mahnaz-meem/geohub
Keywords: geohub
Classifier: Intended Audience :: Developers
Classifier: License :: OSI Approved :: BSD License
Classifier: Natural Language :: English
Classifier: Programming Language :: Python :: 3.8
Classifier: Programming Language :: Python :: 3.9
Classifier: Programming Language :: Python :: 3.10
Classifier: Programming Language :: Python :: 3.11
Classifier: Programming Language :: Python :: 3.12
Requires-Python: >=3.8
License-File: LICENSE
Requires-Dist: numpy
Requires-Dist: ipyleaflet
Requires-Dist: geopandas
Requires-Dist: pandas
Requires-Dist: localtileserver
Requires-Dist: rasterio
Requires-Dist: matplotlib
Requires-Dist: leafmap
Requires-Dist: folium
Requires-Dist: ee
Requires-Dist: earthengine-api >=0.1.398
Provides-Extra: all
Requires-Dist: geohub[extra] ; extra == 'all'
Provides-Extra: extra
Requires-Dist: pandas ; extra == 'extra'
